incyte/__init__.py
incyte/_version.py
incyte/compare.py
incyte/config.py
incyte-1.0.1.dist-info/LICENSE
incyte-1.0.1.dist-info/METADATA
incyte-1.0.1.dist-info/WHEEL
incyte-1.0.1.dist-info/entry_points.txt
incyte-1.0.1.dist-info/top_level.txt
incyte-1.0.1.dist-info/RECORD
