Metadata-Version: 2.1
Name: incyte
Version: 1.0.1
Summary: A stress testing tool for comparing the output of two programs
Home-page: UNKNOWN
License: MIT
Keywords: compare,output,diff,stress testing,testing,software testing,stress tests,stress test tool
Platform: UNKNOWN
Requires-Python: >=3.6
Requires-Dist: rich
